examples/autoagent_distributed_example.py
examples/calculator_agent_example.py
examples/cloud_deployment_example.py
examples/custom_profile_decorator.py
examples/custom_profile_wrap.py
examples/customagent_distributed_example.py
examples/customagent_p2p_example.py
examples/fastapi_integration_example.py
examples/listeneragent_cognitive_discovery_example.py
examples/multi_agent_workflow.py
examples/research_agent_example.py
jarviscore/__init__.py
jarviscore/adapter/__init__.py
jarviscore/adapter/decorator.py
jarviscore/adapter/wrapper.py
jarviscore/cli/__init__.py
jarviscore/cli/__main__.py
jarviscore/cli/check.py
jarviscore/cli/scaffold.py
jarviscore/cli/smoketest.py
jarviscore/config/__init__.py
jarviscore/config/settings.py
jarviscore/context/__init__.py
jarviscore/context/dependency.py
jarviscore/context/jarvis_context.py
jarviscore/context/memory.py
jarviscore/core/__init__.py
jarviscore/core/agent.py
jarviscore/core/mesh.py
jarviscore/core/profile.py
jarviscore/data/.env.example
jarviscore/data/__init__.py
jarviscore/data/examples/autoagent_distributed_example.py
jarviscore/data/examples/calculator_agent_example.py
jarviscore/data/examples/cloud_deployment_example.py
jarviscore/data/examples/customagent_distributed_example.py
jarviscore/data/examples/customagent_p2p_example.py
jarviscore/data/examples/fastapi_integration_example.py
jarviscore/data/examples/listeneragent_cognitive_discovery_example.py
jarviscore/data/examples/multi_agent_workflow.py
jarviscore/data/examples/research_agent_example.py
jarviscore/docs/API_REFERENCE.md
jarviscore/docs/AUTOAGENT_GUIDE.md
jarviscore/docs/CHANGELOG.md
jarviscore/docs/CONFIGURATION.md
jarviscore/docs/CUSTOMAGENT_GUIDE.md
jarviscore/docs/GETTING_STARTED.md
jarviscore/docs/TROUBLESHOOTING.md
jarviscore/docs/USER_GUIDE.md
jarviscore/execution/__init__.py
jarviscore/execution/code_registry.py
jarviscore/execution/generator.py
jarviscore/execution/llm.py
jarviscore/execution/repair.py
jarviscore/execution/result_handler.py
jarviscore_framework-0.3.0.dist-info/licenses/LICENSE
jarviscore_framework-0.3.0.dist-info/METADATA
jarviscore_framework-0.3.0.dist-info/WHEEL
jarviscore_framework-0.3.0.dist-info/top_level.txt
jarviscore_framework-0.3.0.dist-info/RECORD
