Metadata-Version: 2.4
Name: jarviscore-framework
Version: 0.3.0
Summary: Build autonomous AI agents in 3 lines of code. Production-ready orchestration with P2P mesh networking.
Author-email: Ruth Mutua <mutuandinda82@gmail.com>, Muyukani Kizito <muyukani@prescottdata.io>
Maintainer-email: Prescott Data <info@prescottdata.io>
License-Expression: MIT
Project-URL: Homepage, https://github.com/Prescott-Data/jarviscore-framework
Project-URL: Documentation, https://github.com/Prescott-Data/jarviscore-framework/tree/main/jarviscore/docs
Project-URL: Repository, https://github.com/Prescott-Data/jarviscore-framework
Project-URL: Issues, https://github.com/Prescott-Data/jarviscore-framework/issues
Keywords: agents,p2p,llm,distributed,workflow,orchestration
Classifier: Development Status :: 3 - Alpha
Classifier: Intended Audience :: Developers
Classifier: Programming Language :: Python :: 3
Classifier: Programming Language :: Python :: 3.10
Classifier: Programming Language :: Python :: 3.11
Classifier: Programming Language :: Python :: 3.12
Requires-Python: >=3.10
License-File: LICENSE
Requires-Dist: pydantic>=2.0.0
Requires-Dist: pydantic-settings>=2.0.0
Requires-Dist: swim-p2p
Requires-Dist: pyzmq
Requires-Dist: python-dotenv>=1.0.0
Requires-Dist: aiohttp>=3.9.0
Requires-Dist: beautifulsoup4>=4.12.0
Requires-Dist: anthropic>=0.18.0
Requires-Dist: openai>=1.0.0
Requires-Dist: google-genai>=1.0.0
Requires-Dist: httpx>=0.25.0
Provides-Extra: dev
Requires-Dist: pytest>=7.4.0; extra == "dev"
Requires-Dist: pytest-asyncio>=0.21.0; extra == "dev"
Requires-Dist: pytest-cov>=4.1.0; extra == "dev"
Requires-Dist: black>=23.0.0; extra == "dev"
Requires-Dist: mypy>=1.5.0; extra == "dev"
Requires-Dist: ruff>=0.1.0; extra == "dev"
Provides-Extra: all
Requires-Dist: jarviscore[dev]; extra == "all"
Dynamic: license-file
